atip/__init__.py
atip/__main__.py
atip/_version.py
atip/load_sim.py
atip/sim_data_sources.py
atip/simulator.py
atip/utils.py
atip/rings/DBA.mat
atip/rings/DIAD.mat
atip/rings/DIAD_WIG.mat
atip/rings/DIAMOND2SP.lat
atip/rings/HMBA.mat
atip/rings/I04.mat
atip/rings/VMX.mat
atip/rings/VMXSP.mat
atip/rings/VMXSP_WIG.mat
atip/rings/VMX_WIG.mat
atip/rings/create_lattice_matfile.m
atip-0.2.0.dist-info/licenses/LICENSE
atip-0.2.0.dist-info/METADATA
atip-0.2.0.dist-info/WHEEL
atip-0.2.0.dist-info/entry_points.txt
atip-0.2.0.dist-info/top_level.txt
atip-0.2.0.dist-info/RECORD
