Metadata-Version: 2.4
Name: atip
Version: 0.2.0
Summary: Accelerator Toolbox Interface for Pytac
Author-email: Tobyn Nicholls <tobyn.nicholls@diamond.ac.uk>, Phil Smith <philip.smith@diamond.ac.uk>
License:                                  Apache License
Project-URL: GitHub, https://github.com/DiamondLightSource/atip
Classifier: Development Status :: 3 - Alpha
Classifier: License :: OSI Approved :: Apache Software License
Classifier: Programming Language :: Python :: 3.11
Classifier: Programming Language :: Python :: 3.12
Classifier: Programming Language :: Python :: 3.13
Requires-Python: >=3.11
License-File: LICENSE
Requires-Dist: numpy
Requires-Dist: scipy
Requires-Dist: pytac>=0.3.0
Requires-Dist: accelerator-toolbox<0.7.1,>=0.2.0
Requires-Dist: cothread
Requires-Dist: softioc
Provides-Extra: dev
Requires-Dist: copier; extra == "dev"
Requires-Dist: mypy; extra == "dev"
Requires-Dist: myst-parser; extra == "dev"
Requires-Dist: pipdeptree; extra == "dev"
Requires-Dist: pre-commit; extra == "dev"
Requires-Dist: pydata-sphinx-theme>=0.12; extra == "dev"
Requires-Dist: pytest; extra == "dev"
Requires-Dist: pytest-cov; extra == "dev"
Requires-Dist: testfixtures; extra == "dev"
Requires-Dist: ruff; extra == "dev"
Requires-Dist: sphinx-autobuild; extra == "dev"
Requires-Dist: sphinx-copybutton; extra == "dev"
Requires-Dist: sphinx-design; extra == "dev"
Requires-Dist: tox-direct; extra == "dev"
Requires-Dist: types-mock; extra == "dev"
Dynamic: license-file
